minesweeper/__init__.py
minesweeper/base.py
minesweeper/constants.py
minesweeper/exceptions.py
minesweeper/game.py
minesweeper_client-0.2.2.dist-info/METADATA
minesweeper_client-0.2.2.dist-info/WHEEL
minesweeper_client-0.2.2.dist-info/top_level.txt
minesweeper_client-0.2.2.dist-info/RECORD
